{
  "project_info": {
    "project_number": "969281977603",
    "project_id": "cmsc23-todo-app-kbbpunzalan",
    "storage_bucket": "cmsc23-todo-app-kbbpunzalan.appspot.com"
  },
  "client": [
    {
      "client_info": {
        "mobilesdk_app_id": "1:969281977603:android:d85657729fd0e65f21bd36",
        "android_client_info": {
          "package_name": "com.example.week7_networking_discussion"
        }
      },
      "oauth_client": [
        {
          "client_id": "969281977603-0aijt10v7bt9gb7lioj54jaqnj0em5la.apps.googleusercontent.com",
          "client_type": 3
        }
      ],
      "api_key": [
        {
          "current_key": "AIzaSyA7GZ3zyqmblMMOqGkvAnTu9hk5uVhqCK4"
        }
      ],
      "services": {
        "appinvite_service": {
          "other_platform_oauth_client": [
            {
              "client_id": "969281977603-0aijt10v7bt9gb7lioj54jaqnj0em5la.apps.googleusercontent.com",
              "client_type": 3
            },
            {
              "client_id": "969281977603-noln212d0s41void65bc688ath7vffmh.apps.googleusercontent.com",
              "client_type": 2,
              "ios_info": {
                "bundle_id": "com.example.week7NetworkingDiscussion"
              }
            }
          ]
        }
      }
    }
  ],
  "configuration_version": "1"
}